alertapi/__init__.py
alertapi/_about.py
alertapi/errors.py
alertapi/images.py
alertapi/snowflakes.py
alertapi/states.py
alertapi/api/__init__.py
alertapi/api/entity_factory.py
alertapi/api/event_factory.py
alertapi/api/event_manager.py
alertapi/api/http.py
alertapi/events/__init__.py
alertapi/events/base_events.py
alertapi/impl/__init__.py
alertapi/impl/client.py
alertapi/impl/entity_factory.py
alertapi/impl/event_factory.py
alertapi/impl/event_manager.py
alertapi/impl/http.py
alertapi/internal/__init__.py
alertapi/internal/aio.py
alertapi/internal/converters.py
alertapi/internal/data_binding.py
alertapi/internal/routes.py
alertapi-0.0.4.dist-info/LICENSE
alertapi-0.0.4.dist-info/METADATA
alertapi-0.0.4.dist-info/WHEEL
alertapi-0.0.4.dist-info/top_level.txt
alertapi-0.0.4.dist-info/RECORD
