Metadata-Version: 2.1
Name: alertapi
Version: 0.0.4
Summary: The Air Raid Alert API wrapper for Python3
Home-page: https://github.com/CrispCrow/AlertAPI
Author: CrispCrow
Author-email: minikslyh@gmail.com
License: MIT
Project-URL: Source (GitHub), https://github.com/CrispCrow/AlertAPI
Project-URL: Issue Tracker, https://github.com/CrispCrow/AlertAPI/issues
Platform: UNKNOWN
Classifier: Programming Language :: Python :: 3.10
Classifier: Programming Language :: Python :: 3.8
Classifier: Programming Language :: Python :: 3.9
Classifier: Programming Language :: Python :: Implementation :: CPython
Classifier: Natural Language :: English
Classifier: License :: OSI Approved :: MIT License
Classifier: Operating System :: OS Independent
Requires-Python: >=3.8
License-File: LICENSE
Requires-Dist: attrs (==21.4.0)
Requires-Dist: aiohttp (==3.8.1)
Requires-Dist: aiohttp-sse-client (==0.2.1)
